LICENSE.txt
README.md
django_ptpython/__init__.py
django_ptpython/apps.py
django_ptpython/management/commands/shell.py
django_ptpython-1.0.2.dist-info/LICENSE.txt
django_ptpython-1.0.2.dist-info/WHEEL
django_ptpython-1.0.2.dist-info/METADATA
django_ptpython-1.0.2.dist-info/RECORD
