Metadata-Version: 2.1
Name: django-ptpython
Version: 1.0.2
Summary: PtPython as default Django shell.
Home-page: https://github.com/reganto/django-ptpython
License: Apache-2.0
Keywords: Django,Python
Author: Reganto
Author-email: tell.reganto@gmail.com
Requires-Python: >=3.8,<4.0
Classifier: Environment :: Web Environment
Classifier: Intended Audience :: Developers
Classifier: License :: OSI Approved :: Apache Software License
Classifier: Operating System :: OS Independent
Classifier: Programming Language :: Python
Classifier: Programming Language :: Python :: 3
Classifier: Programming Language :: Python :: 3 :: Only
Classifier: Programming Language :: Python :: 3.10
Classifier: Programming Language :: Python :: 3.4
Classifier: Programming Language :: Python :: 3.5
Classifier: Programming Language :: Python :: 3.6
Classifier: Programming Language :: Python :: 3.7
Classifier: Programming Language :: Python :: 3.8
Classifier: Programming Language :: Python :: 3.9
Classifier: Topic :: Software Development :: Libraries :: Python Modules
Requires-Dist: django (>=3.2.14,<4.0.0)
Requires-Dist: ptpython (>=3.0,<4.0)
Project-URL: Bug Tracker, https://github.com/reganto/django-ptpython/issues
